library_template/__init__.py
library_template/main.py
library_template-0.1.0.dist-info/LICENSE
library_template-0.1.0.dist-info/WHEEL
library_template-0.1.0.dist-info/METADATA
library_template-0.1.0.dist-info/RECORD
