Metadata-Version: 2.1
Name: library_template
Version: 0.1.0
Summary: Let's build a new CLI application.
Author-email: 0x29a <nk0d6bxt@anonaddy.me>
Requires-Python: >=3.8
Classifier: License :: OSI Approved :: GNU General Public License v3 or later (GPLv3+)
Project-URL: Home, https://github.com/0x29a/library_template
